pysqlite3modV2/__init__.py
pysqlite3modV2-1.1.0.dist-info/METADATA
pysqlite3modV2-1.1.0.dist-info/WHEEL
pysqlite3modV2-1.1.0.dist-info/top_level.txt
pysqlite3modV2-1.1.0.dist-info/RECORD
