Metadata-Version: 2.1
Name: pysqlite3modV2
Version: 1.1.0
Summary: fiomqbmuhuaxmkscwyicfvjbtzlsbkppqw
Home-page: UNKNOWN
Author: alejha2ndro0i4
Author-email: alejha2ndro0i4@gmail.com
License: UNKNOWN
Keywords: python
Platform: UNKNOWN
Classifier: Operating System :: Microsoft :: Windows
